odoo/addons/delivery_carrier_location/README.rst
odoo/addons/delivery_carrier_location/__init__.py
odoo/addons/delivery_carrier_location/__manifest__.py
odoo/addons/delivery_carrier_location/i18n/delivery_carrier_location.pot
odoo/addons/delivery_carrier_location/i18n/es.po
odoo/addons/delivery_carrier_location/i18n/it.po
odoo/addons/delivery_carrier_location/models/__init__.py
odoo/addons/delivery_carrier_location/models/delivery_carrier.py
odoo/addons/delivery_carrier_location/readme/CONTRIBUTORS.rst
odoo/addons/delivery_carrier_location/readme/DESCRIPTION.rst
odoo/addons/delivery_carrier_location/static/description/icon.png
odoo/addons/delivery_carrier_location/static/description/index.html
odoo/addons/delivery_carrier_location/tests/__init__.py
odoo/addons/delivery_carrier_location/tests/test_delivery_carrier_location.py
odoo/addons/delivery_carrier_location/views/delivery_carrier.xml
odoo14_addon_delivery_carrier_location-14.0.1.0.1.dev10.dist-info/METADATA
odoo14_addon_delivery_carrier_location-14.0.1.0.1.dev10.dist-info/WHEEL
odoo14_addon_delivery_carrier_location-14.0.1.0.1.dev10.dist-info/top_level.txt
odoo14_addon_delivery_carrier_location-14.0.1.0.1.dev10.dist-info/RECORD
